<?xml version="1.0" encoding="utf-8"?>
<deployment>
  <id>0d8885670373f970210fff819a2a4411af3f9dbd1758594816662</id>
  <author>ramy-atawia</author>
  <deployer>GitHub</deployer>
  <authorEmail />
  <message>{"type":"Deployment","sha":"0d8885670373f970210fff819a2a4411af3f9dbd","repoName":"ramy-atawia/word-addin-mcp","actor":"ramy-atawia","slotName":"production"}</message>
  <progress />
  <status>Success</status>
  <statusText />
  <lastSuccessEndTime>2025-09-23T02:34:26.5343161Z</lastSuccessEndTime>
  <receivedTime>2025-09-23T02:34:26.5343161Z</receivedTime>
  <startTime>2025-09-23T02:34:26.5343161Z</startTime>
  <endTime>2025-09-23T02:34:26.5343161Z</endTime>
  <complete>True</complete>
  <is_temp>False</is_temp>
  <is_readonly>True</is_readonly>
  <buildSummary />
</deployment>